bagels/__init__.py
bagels/__main__.py
bagels/app.py
bagels/bagel.py
bagels/config.py
bagels/constants.py
bagels/home.py
bagels/locations.py
bagels/manager.py
bagels/provider.py
bagels/textualrun.py
bagels/themes.py
bagels/versioning.py
bagels/components/autocomplete.py
bagels/components/bagel.py
bagels/components/barchart.py
bagels/components/datatable.py
bagels/components/fields.py
bagels/components/header.py
bagels/components/indicators.py
bagels/components/jump_overlay.py
bagels/components/jumper.py
bagels/components/percentage_bar.py
bagels/components/modules/accountmode.py
bagels/components/modules/budgets.py
bagels/components/modules/categories.py
bagels/components/modules/datemode.py
bagels/components/modules/incomemode.py
bagels/components/modules/insights.py
bagels/components/modules/people.py
bagels/components/modules/templates.py
bagels/components/modules/welcome.py
bagels/components/modules/records/__init__.py
bagels/components/modules/records/_cud.py
bagels/components/modules/records/_table_builder.py
bagels/components/modules/spending/__init__.py
bagels/components/modules/spending/plots.py
bagels/components/tplot/__init__.py
bagels/components/tplot/__main__.py
bagels/components/tplot/plot.py
bagels/components/tplot/plotext_plot.py
bagels/components/tplot/py.typed
bagels/components/tplot/plotext/__init__.py
bagels/components/tplot/plotext/__init__.pyi
bagels/components/tplot/plotext/_figure.py
bagels/components/tplot/plotext/_figure.pyi
bagels/forms/account_forms.py
bagels/forms/category_form.py
bagels/forms/form.py
bagels/forms/person_forms.py
bagels/forms/record_forms.py
bagels/forms/recordtemplate_forms.py
bagels/forms/transfer_forms.py
bagels/managers/accounts.py
bagels/managers/categories.py
bagels/managers/persons.py
bagels/managers/record_templates.py
bagels/managers/records.py
bagels/managers/samples.py
bagels/managers/splits.py
bagels/managers/utils.py
bagels/migrations/migrate_actualbudget.py
bagels/modals/base_widget.py
bagels-0.3.12.dist-info/METADATA
bagels-0.3.12.dist-info/WHEEL
bagels-0.3.12.dist-info/entry_points.txt
bagels-0.3.12.dist-info/licenses/LICENSE
bagels-0.3.12.dist-info/RECORD
