Metadata-Version: 2.4
Name: Bagels
Version: 0.3.12
Summary: Powerful terminal expense tracker.
Project-URL: Homepage, https://github.com/EnhancedJax/Bagels
Project-URL: Repository, https://github.com/EnhancedJax/Bagels
Project-URL: Issues, https://github.com/EnhancedJax/Bagels/issues
Project-URL: Documentation, https://github.com/EnhancedJax/Bagels/blob/main/README.md
Author-email: Jax <enhancedjax@gmail.com>
License:                     GNU GENERAL PUBLIC LICENSE
License-File: LICENSE
Keywords: UV,cli,expense-tracker,python,python3,ssh,terminal,textual,tui
Requires-Python: >=3.13
Requires-Dist: aiohappyeyeballs<3.0,>=2.0
Requires-Dist: aiohttp-jinja2<2.0,>=1.0
Requires-Dist: aiohttp<4.0,>=3.0
Requires-Dist: aiosignal<2.0,>=1.0
Requires-Dist: annotated-types<1.0,>=0.0
Requires-Dist: attrs<25.0,>=24.0
Requires-Dist: blinker<2.0,>=1.0
Requires-Dist: click-default-group<2.0,>=1.2
Requires-Dist: click<9.0,>=8.0
Requires-Dist: frozenlist<2.0,>=1.0
Requires-Dist: idna<4.0,>=3.0
Requires-Dist: itsdangerous<3.0,>=2.0
Requires-Dist: linkify-it-py<3.0,>=2.0
Requires-Dist: markdown-it-py<4.0,>=3.0
Requires-Dist: markupsafe<4.0,>=3.0
Requires-Dist: mdit-py-plugins<1.0,>=0.4
Requires-Dist: mdurl<1.0,>=0.1
Requires-Dist: msgpack<2.0,>=1.0
Requires-Dist: multidict<7.0,>=6.0
Requires-Dist: numpy<3.0,>=2.0
Requires-Dist: packaging<24.0,>=23.0
Requires-Dist: platformdirs<5.0,>=4.0
Requires-Dist: plotext<6.0,>=5.0
Requires-Dist: propcache<1.0,>=0.2
Requires-Dist: pydantic-core<3.0,>=2.0
Requires-Dist: pydantic<3.0,>=2.0
Requires-Dist: pygments<3.0,>=2.0
Requires-Dist: python-dateutil<3.0,>=2.0
Requires-Dist: pyyaml<7.0,>=6.0
Requires-Dist: requests<3.0,>=2.0
Requires-Dist: rich<14.0,>=13.0
Requires-Dist: sqlalchemy<3.0,>=2.0
Requires-Dist: textual<2.0,>=1.0
Requires-Dist: tomli<3.0,>=2.0
Requires-Dist: typing-extensions<5.0,>=4.0
Requires-Dist: uc-micro-py<2.0,>=1.0
Requires-Dist: werkzeug<4.0,>=3.0
Requires-Dist: xdg-base-dirs<7.0,>=6.0
Requires-Dist: yarl<2.0,>=1.0
